Metadata-Version: 2.1
Name: aqvify
Version: 0.1.1
Summary: Read values from Aqvify through their API.
Home-page: http://github.com/ptz0n/python-aqvify
Author: Erik Eng
Author-email: erik@eng.se
License: MIT
Keywords: home automation aqvify
Classifier: Development Status :: 4 - Beta
Classifier: Intended Audience :: Developers
Classifier: Topic :: Home Automation
Classifier: License :: OSI Approved :: MIT License
Classifier: Programming Language :: Python :: 3.11
License-File: LICENSE
